cv2_multistack/LICENSE
cv2_multistack/README.MD
cv2_multistack/__init__.py
cv2_multistack/requirements.txt
cv2_multistack/thirdparty.json
cv2_multistack-0.10.dist-info/LICENSE.rst
cv2_multistack-0.10.dist-info/METADATA
cv2_multistack-0.10.dist-info/WHEEL
cv2_multistack-0.10.dist-info/top_level.txt
cv2_multistack-0.10.dist-info/RECORD
